terminal_playing_cards/__init__.py
terminal_playing_cards/__main__.py
terminal_playing_cards/card.py
terminal_playing_cards/config.py
terminal_playing_cards/deck.py
terminal_playing_cards/utils.py
terminal_playing_cards/view.py
terminal_playing_cards-0.1.0.dist-info/LICENSE
terminal_playing_cards-0.1.0.dist-info/WHEEL
terminal_playing_cards-0.1.0.dist-info/METADATA
terminal_playing_cards-0.1.0.dist-info/RECORD
