Metadata-Version: 2.1
Name: terminal-playing-cards
Version: 0.1.0
Summary: Create card games for the terminal
Home-page: https://github.com/pwildenhain/terminal_playing_cards
License: MIT
Keywords: cards
Author: Paul Wildenhain
Author-email: pwildenhain@gmail.com
Requires-Python: >=3.6,<4.0
Classifier: License :: OSI Approved :: MIT License
Classifier: Programming Language :: Python :: 3
Classifier: Programming Language :: Python :: 3.6
Classifier: Programming Language :: Python :: 3.7
Requires-Dist: colorama (>=0.4.1,<0.5.0)
Project-URL: Repository, https://github.com/pwildenhain/terminal_playing_cards
